textx_dsldoc/__init__.py
textx_dsldoc/converters.py
textx_dsldoc/render_arpeggio.py
textx_dsldoc/render_metamodel.py
textx_dsldoc/render_utils.py
textx_dsldoc/textx_integration.py
textx_dsldoc-0.0.1.dist-info/METADATA
textx_dsldoc-0.0.1.dist-info/WHEEL
textx_dsldoc-0.0.1.dist-info/entry_points.txt
textx_dsldoc-0.0.1.dist-info/top_level.txt
textx_dsldoc-0.0.1.dist-info/RECORD
