Metadata-Version: 2.1
Name: textx-dsldoc
Version: 0.0.1
Summary: Autogeneration of DSL documentation for TextX
Home-page: https://github.com/aluriak/textx-dsldoc
Author: Lucas Bourneuf
Author-email: lucas.bourneuf@laposte.net
License: GPL
Keywords: textx subcommand,doc generation
Platform: UNKNOWN
Classifier: Development Status :: 3 - Alpha
Classifier: Programming Language :: Python :: 3
Classifier: Programming Language :: Python :: 3.5
Classifier: Programming Language :: Python :: 3.6
Classifier: Programming Language :: Python :: 3.7
Requires-Dist: Click (==7.0)
Requires-Dist: Markdown (==3.0.1)
Requires-Dist: exrex (==0.10.5)
Requires-Dist: textX (==1.9.0)
